[
    {
      "title": "Movement",
      "subtitle": "Rebirth",
      "card_filename": "Glass Port.png",
      "difficulty": "1-1",
      "modes": "All",
      "is_no_cmod": false,
      "banner_filename": "1-1.png"
    },
    {
      "title": "Pummel",
      "subtitle": "Rebirth",
      "card_filename": "Glass Port.png",
      "difficulty": "1-2",
      "modes": "All",
      "is_no_cmod": false,
      "banner_filename": "1-2.png"
    },
    {
      "title": "Gunner",
      "subtitle": "Rebirth",
      "card_filename": "Glass Port.png",
      "difficulty": "1-3",
      "modes": "All",
      "is_no_cmod": false,
      "banner_filename": "1-3.png"
    },
    {
      "title": "Cascade",
      "subtitle": "Rebirth",
      "card_filename": "Glass Port.png",
      "difficulty": "1-4",
      "modes": "All",
      "is_no_cmod": false,
      "banner_filename": "1-4.png"
    },
    {
      "title": "Elevate",
      "subtitle": "Rebirth",
      "card_filename": "Glass Port.png",
      "difficulty": "1-5",
      "modes": "All",
      "is_no_cmod": false,
      "banner_filename": "1-5.png"
    },
    {
      "title": "Bounce",
      "subtitle": "Rebirth",
      "card_filename": "Glass Port.png",
      "difficulty": "1-6",
      "modes": "All",
      "is_no_cmod": false,
      "banner_filename": "1-6.png"
    },
    {
      "title": "Purify",
      "subtitle": "Rebirth",
      "card_filename": "Glass Port.png",
      "difficulty": "1-7",
      "modes": "All",
      "is_no_cmod": false,
      "banner_filename": "1-7.png"
    },
    {
      "title": "Climb",
      "subtitle": "Rebirth",
      "card_filename": "Glass Port.png",
      "difficulty": "1-8",
      "modes": "All",
      "is_no_cmod": false,
      "banner_filename": "1-8.png"
    },
    {
      "title": "Fasttrack",
      "subtitle": "Rebirth",
      "card_filename": "Glass Port.png",
      "difficulty": "1-9",
      "modes": "All",
      "is_no_cmod": false,
      "banner_filename": "1-9.png"
    },
    {
      "title": "Glass Port",
      "subtitle": "Rebirth",
      "card_filename": "Glass Port.png",
      "difficulty": "1-10",
      "modes": "All",
      "is_no_cmod": false,
      "banner_filename": "1-10.png"
    },
    {
      "title": "Take Flight",
      "subtitle": "Killer Inside",
      "card_filename": "Lower Heaven.png",
      "difficulty": "2-1",
      "modes": "All",
      "is_no_cmod": false,
      "banner_filename": "2-1.png"
    },
    {
      "title": "Godspeed",
      "subtitle": "Killer Inside",
      "card_filename": "Lower Heaven.png",
      "difficulty": "2-2",
      "modes": "All",
      "is_no_cmod": false,
      "banner_filename": "2-2.png"
    },
    {
      "title": "Dasher",
      "subtitle": "Killer Inside",
      "card_filename": "Lower Heaven.png",
      "difficulty": "2-3",
      "modes": "All",
      "is_no_cmod": false,
      "banner_filename": "2-3.png"
    },
    {
      "title": "Thrasher",
      "subtitle": "Killer Inside",
      "card_filename": "Lower Heaven.png",
      "difficulty": "2-4",
      "modes": "All",
      "is_no_cmod": false,
      "banner_filename": "2-4.png"
    },
    {
      "title": "Outstretched",
      "subtitle": "Killer Inside",
      "card_filename": "Lower Heaven.png",
      "difficulty": "2-5",
      "modes": "All",
      "is_no_cmod": false,
      "banner_filename": "2-5.png"
    },
    {
      "title": "Smackdown",
      "subtitle": "Killer Inside",
      "card_filename": "Lower Heaven.png",
      "difficulty": "2-6",
      "modes": "All",
      "is_no_cmod": false,
      "banner_filename": "2-6.png"
    },
    {
      "title": "Catwalk",
      "subtitle": "Killer Inside",
      "card_filename": "Lower Heaven.png",
      "difficulty": "2-7",
      "modes": "All",
      "is_no_cmod": false,
      "banner_filename": "2-7.png"
    },
    {
      "title": "Fastlane",
      "subtitle": "Killer Inside",
      "card_filename": "Lower Heaven.png",
      "difficulty": "2-8",
      "modes": "All",
      "is_no_cmod": false,
      "banner_filename": "2-8.png"
    },
    {
      "title": "Distinguish",
      "subtitle": "Killer Inside",
      "card_filename": "Lower Heaven.png",
      "difficulty": "2-9",
      "modes": "All",
      "is_no_cmod": false,
      "banner_filename": "2-9.png"
    },
    {
      "title": "Dancer",
      "subtitle": "Killer Inside",
      "card_filename": "Lower Heaven.png",
      "difficulty": "2-10",
      "modes": "All",
      "is_no_cmod": false,
      "banner_filename": "2-10.png"
    },
    {
      "title": "Guardian",
      "subtitle": "Only Shallow",
      "card_filename": "Lower Heaven2.png",
      "difficulty": "3-1",
      "modes": "All",
      "is_no_cmod": false,
      "banner_filename": "3-1.png"
    },
    {
      "title": "Stomp",
      "subtitle": "Only Shallow",
      "card_filename": "Lower Heaven2.png",
      "difficulty": "3-2",
      "modes": "All",
      "is_no_cmod": false,
      "banner_filename": "3-2.png"
    },
    {
      "title": "Jumper",
      "subtitle": "Only Shallow",
      "card_filename": "Lower Heaven2.png",
      "difficulty": "3-3",
      "modes": "All",
      "is_no_cmod": false,
      "banner_filename": "3-3.png"
    },
    {
      "title": "Dash Tower",
      "subtitle": "Only Shallow",
      "card_filename": "Lower Heaven2.png",
      "difficulty": "3-4",
      "modes": "All",
      "is_no_cmod": false,
      "banner_filename": "3-4.png"
    },
    {
      "title": "Descent",
      "subtitle": "Only Shallow",
      "card_filename": "Lower Heaven2.png",
      "difficulty": "3-5",
      "modes": "All",
      "is_no_cmod": false,
      "banner_filename": "3-5.png"
    },
    {
      "title": "Driller",
      "subtitle": "Only Shallow",
      "card_filename": "Lower Heaven2.png",
      "difficulty": "3-6",
      "modes": "All",
      "is_no_cmod": false,
      "banner_filename": "3-6.png"
    },
    {
      "title": "Canals",
      "subtitle": "Only Shallow",
      "card_filename": "Lower Heaven2.png",
      "difficulty": "3-7",
      "modes": "All",
      "is_no_cmod": false,
      "banner_filename": "3-7.png"
    },
    {
      "title": "Sprint",
      "subtitle": "Only Shallow",
      "card_filename": "Lower Heaven2.png",
      "difficulty": "3-8",
      "modes": "All",
      "is_no_cmod": false,
      "banner_filename": "3-8.png"
    },
    {
      "title": "Mountain",
      "subtitle": "Only Shallow",
      "card_filename": "Lower Heaven2.png",
      "difficulty": "3-9",
      "modes": "All",
      "is_no_cmod": false,
      "banner_filename": "3-9.png"
    },
    {
      "title": "Superkinetic",
      "subtitle": "Only Shallow",
      "card_filename": "Lower Heaven2.png",
      "difficulty": "3-10",
      "modes": "All",
      "is_no_cmod": false,
      "banner_filename": "3-10.png"
    },
    {
      "title": "Arrival",
      "subtitle": "The Old City",
      "card_filename": "Old City.png",
      "difficulty": "4-1",
      "modes": "All",
      "is_no_cmod": false,
      "banner_filename": "4-1.png"
    },
    {
      "title": "Forgotten City",
      "subtitle": "The Old City",
      "card_filename": "Old City.png",
      "difficulty": "4-2",
      "modes": "All",
      "is_no_cmod": false,
      "banner_filename": "4-2.png"
    },
    {
      "title": "The Clocktower",
      "subtitle": "The Old City",
      "card_filename": "Old City.png",
      "difficulty": "4-3",
      "modes": "All",
      "is_no_cmod": true,
      "banner_filename": "4-3.png"
    },
    {
      "title": "Fireball",
      "subtitle": "The Burn That Cures",
      "card_filename": "Lower Heaven2.png",
      "difficulty": "5-1",
      "modes": "All",
      "is_no_cmod": false,
      "banner_filename": "5-1.png"
    },
    {
      "title": "Ringer",
      "subtitle": "The Burn That Cures",
      "card_filename": "Lower Heaven2.png",
      "difficulty": "5-2",
      "modes": "All",
      "is_no_cmod": false,
      "banner_filename": "5-2.png"
    },
    {
      "title": "Cleaner",
      "subtitle": "The Burn That Cures",
      "card_filename": "Lower Heaven2.png",
      "difficulty": "5-3",
      "modes": "All",
      "is_no_cmod": false,
      "banner_filename": "5-3.png"
    },
    {
      "title": "Warehouse",
      "subtitle": "The Burn That Cures",
      "card_filename": "Lower Heaven2.png",
      "difficulty": "5-4",
      "modes": "All",
      "is_no_cmod": false,
      "banner_filename": "5-4.png"
    },
    {
      "title": "Boom",
      "subtitle": "The Burn That Cures",
      "card_filename": "Lower Heaven2.png",
      "difficulty": "5-5",
      "modes": "All",
      "is_no_cmod": false,
      "banner_filename": "5-5.png"
    },
    {
      "title": "Streets",
      "subtitle": "The Burn That Cures",
      "card_filename": "Lower Heaven2.png",
      "difficulty": "5-6",
      "modes": "All",
      "is_no_cmod": false,
      "banner_filename": "5-6.png"
    },
    {
      "title": "Steps",
      "subtitle": "The Burn That Cures",
      "card_filename": "Lower Heaven2.png",
      "difficulty": "5-7",
      "modes": "All",
      "is_no_cmod": false,
      "banner_filename": "5-7.png"
    },
    {
      "title": "Demolition",
      "subtitle": "The Burn That Cures",
      "card_filename": "Lower Heaven2.png",
      "difficulty": "5-8",
      "modes": "All",
      "is_no_cmod": false,
      "banner_filename": "5-8.png"
    },
    {
      "title": "Arcs",
      "subtitle": "The Burn That Cures",
      "card_filename": "Lower Heaven2.png",
      "difficulty": "5-9",
      "modes": "All",
      "is_no_cmod": false,
      "banner_filename": "5-9.png"
    },
    {
      "title": "Apartment",
      "subtitle": "The Burn That Cures",
      "card_filename": "Lower Heaven2.png",
      "difficulty": "5-10",
      "modes": "All",
      "is_no_cmod": false,
      "banner_filename": "5-10.png"
    },
    {
      "title": "Hanging Gardens",
      "subtitle": "Covenant",
      "card_filename": "Hanging Gardens.png",
      "difficulty": "6-1",
      "modes": "All",
      "is_no_cmod": false,
      "banner_filename": "6-1.png"
    },
    {
      "title": "Tangled",
      "subtitle": "Covenant",
      "card_filename": "Hanging Gardens.png",
      "difficulty": "6-2",
      "modes": "All",
      "is_no_cmod": false,
      "banner_filename": "6-2.png"
    },
    {
      "title": "Waterworks",
      "subtitle": "Covenant",
      "card_filename": "Hanging Gardens.png",
      "difficulty": "6-3",
      "modes": "All",
      "is_no_cmod": false,
      "banner_filename": "6-3.png"
    },
    {
      "title": "Killswitch",
      "subtitle": "Covenant",
      "card_filename": "Hanging Gardens.png",
      "difficulty": "6-4",
      "modes": "All",
      "is_no_cmod": false,
      "banner_filename": "6-4.png"
    },
    {
      "title": "Falling",
      "subtitle": "Covenant",
      "card_filename": "Hanging Gardens.png",
      "difficulty": "6-5",
      "modes": "All",
      "is_no_cmod": false,
      "banner_filename": "6-5.png"
    },
    {
      "title": "Shocker",
      "subtitle": "Covenant",
      "card_filename": "Hanging Gardens.png",
      "difficulty": "6-6",
      "modes": "All",
      "is_no_cmod": false,
      "banner_filename": "6-6.png"
    },
    {
      "title": "Bouquet",
      "subtitle": "Covenant",
      "card_filename": "Hanging Gardens.png",
      "difficulty": "6-7",
      "modes": "All",
      "is_no_cmod": false,
      "banner_filename": "6-7.png"
    },
    {
      "title": "Prepare",
      "subtitle": "Covenant",
      "card_filename": "Hanging Gardens.png",
      "difficulty": "6-8",
      "modes": "All",
      "is_no_cmod": false,
      "banner_filename": "6-8.png"
    },
    {
      "title": "Triptrack",
      "subtitle": "Covenant",
      "card_filename": "Hanging Gardens.png",
      "difficulty": "6-9",
      "modes": "All",
      "is_no_cmod": false,
      "banner_filename": "6-9.png"
    },
    {
      "title": "Race",
      "subtitle": "Covenant",
      "card_filename": "Hanging Gardens.png",
      "difficulty": "6-10",
      "modes": "All",
      "is_no_cmod": false,
      "banner_filename": "6-10.png"
    },
    {
      "title": "Bubble",
      "subtitle": "Reckoning",
      "card_filename": "Hanging Gardens.png",
      "difficulty": "7-1",
      "modes": "All",
      "is_no_cmod": false,
      "banner_filename": "7-1.png"
    },
    {
      "title": "Shield",
      "subtitle": "Reckoning",
      "card_filename": "Hanging Gardens.png",
      "difficulty": "7-2",
      "modes": "All",
      "is_no_cmod": false,
      "banner_filename": "7-2.png"
    },
    {
      "title": "Overlook",
      "subtitle": "Reckoning",
      "card_filename": "Hanging Gardens.png",
      "difficulty": "7-3",
      "modes": "All",
      "is_no_cmod": false,
      "banner_filename": "7-3.png"
    },
    {
      "title": "Pop",
      "subtitle": "Reckoning",
      "card_filename": "Hanging Gardens.png",
      "difficulty": "7-4",
      "modes": "All",
      "is_no_cmod": false,
      "banner_filename": "7-4.png"
    },
    {
      "title": "Minefield",
      "subtitle": "Reckoning",
      "card_filename": "Hanging Gardens.png",
      "difficulty": "7-5",
      "modes": "All",
      "is_no_cmod": false,
      "banner_filename": "7-5.png"
    },
    {
      "title": "Mimic",
      "subtitle": "Reckoning",
      "card_filename": "Hanging Gardens.png",
      "difficulty": "7-6",
      "modes": "All",
      "is_no_cmod": false,
      "banner_filename": "7-6.png"
    },
    {
      "title": "Trigger",
      "subtitle": "Reckoning",
      "card_filename": "Hanging Gardens.png",
      "difficulty": "7-7",
      "modes": "All",
      "is_no_cmod": false,
      "banner_filename": "7-7.png"
    },
    {
      "title": "Greenhouse",
      "subtitle": "Reckoning",
      "card_filename": "Hanging Gardens.png",
      "difficulty": "7-8",
      "modes": "All",
      "is_no_cmod": false,
      "banner_filename": "7-8.png"
    },
    {
      "title": "Sweep",
      "subtitle": "Reckoning",
      "card_filename": "Hanging Gardens.png",
      "difficulty": "7-9",
      "modes": "All",
      "is_no_cmod": false,
      "banner_filename": "7-9.png"
    },
    {
      "title": "Fuse",
      "subtitle": "Reckoning",
      "card_filename": "Hanging Gardens.png",
      "difficulty": "7-10",
      "modes": "All",
      "is_no_cmod": false,
      "banner_filename": "7-10.png"
    },
    {
      "title": "Heaven’s Edge",
      "subtitle": "Benediction",
      "card_filename": "Heaven's Edge.png",
      "difficulty": "8-1",
      "modes": "All",
      "is_no_cmod": false,
      "banner_filename": "8-1.png"
    },
    {
      "title": "Zipline",
      "subtitle": "Benediction",
      "card_filename": "Heaven's Edge.png",
      "difficulty": "8-2",
      "modes": "All",
      "is_no_cmod": false,
      "banner_filename": "8-2.png"
    },
    {
      "title": "Swing",
      "subtitle": "Benediction",
      "card_filename": "Heaven's Edge.png",
      "difficulty": "8-3",
      "modes": "All",
      "is_no_cmod": false,
      "banner_filename": "8-3.png"
    },
    {
      "title": "Chute",
      "subtitle": "Benediction",
      "card_filename": "Heaven's Edge.png",
      "difficulty": "8-4",
      "modes": "All",
      "is_no_cmod": true,
      "banner_filename": "8-4.png"
    },
    {
      "title": "Crash",
      "subtitle": "Benediction",
      "card_filename": "Heaven's Edge.png",
      "difficulty": "8-5",
      "modes": "All",
      "is_no_cmod": false,
      "banner_filename": "8-5.png"
    },
    {
      "title": "Ascent",
      "subtitle": "Benediction",
      "card_filename": "Heaven's Edge.png",
      "difficulty": "8-6",
      "modes": "All",
      "is_no_cmod": false,
      "banner_filename": "8-6.png"
    },
    {
      "title": "Straightaway",
      "subtitle": "Benediction",
      "card_filename": "Heaven's Edge.png",
      "difficulty": "8-7",
      "modes": "All",
      "is_no_cmod": true,
      "banner_filename": "8-7.png"
    },
    {
      "title": "Firecracker",
      "subtitle": "Benediction",
      "card_filename": "Heaven's Edge.png",
      "difficulty": "8-8",
      "modes": "All",
      "is_no_cmod": false,
      "banner_filename": "8-8.png"
    },
    {
      "title": "Streak",
      "subtitle": "Benediction",
      "card_filename": "Heaven's Edge.png",
      "difficulty": "8-9",
      "modes": "All",
      "is_no_cmod": false,
      "banner_filename": "8-9.png"
    },
    {
      "title": "Mirror",
      "subtitle": "Benediction",
      "card_filename": "Heaven's Edge.png",
      "difficulty": "8-10",
      "modes": "All",
      "is_no_cmod": false,
      "banner_filename": "8-10.png"
    },
    {
      "title": "Escalation",
      "subtitle": "Apocrypha",
      "card_filename": "Heaven's Edge.png",
      "difficulty": "9-1",
      "modes": "All",
      "is_no_cmod": false,
      "banner_filename": "9-1.png"
    },
    {
      "title": "Bolt",
      "subtitle": "Apocrypha",
      "card_filename": "Heaven's Edge.png",
      "difficulty": "9-2",
      "modes": "All",
      "is_no_cmod": false,
      "banner_filename": "9-2.png"
    },
    {
      "title": "Godstreak",
      "subtitle": "Apocrypha",
      "card_filename": "Heaven's Edge.png",
      "difficulty": "9-3",
      "modes": "All",
      "is_no_cmod": false,
      "banner_filename": "9-3.png"
    },
    {
      "title": "Plunge",
      "subtitle": "Apocrypha",
      "card_filename": "Heaven's Edge.png",
      "difficulty": "9-4",
      "modes": "All",
      "is_no_cmod": false,
      "banner_filename": "9-4.png"
    },
    {
      "title": "Mayhem",
      "subtitle": "Apocrypha",
      "card_filename": "Heaven's Edge.png",
      "difficulty": "9-5",
      "modes": "All",
      "is_no_cmod": false,
      "banner_filename": "9-5.png"
    },
    {
      "title": "Barrage",
      "subtitle": "Apocrypha",
      "card_filename": "Heaven's Edge.png",
      "difficulty": "9-6",
      "modes": "All",
      "is_no_cmod": false,
      "banner_filename": "9-6.png"
    },
    {
      "title": "Estate",
      "subtitle": "Apocrypha",
      "card_filename": "Heaven's Edge.png",
      "difficulty": "9-7",
      "modes": "All",
      "is_no_cmod": false,
      "banner_filename": "9-7.png"
    },
    {
      "title": "Trapwire",
      "subtitle": "Apocrypha",
      "card_filename": "Heaven's Edge.png",
      "difficulty": "9-8",
      "modes": "All",
      "is_no_cmod": false,
      "banner_filename": "9-8.png"
    },
    {
      "title": "Ricochet",
      "subtitle": "Apocrypha",
      "card_filename": "Heaven's Edge.png",
      "difficulty": "9-9",
      "modes": "All",
      "is_no_cmod": false,
      "banner_filename": "9-9.png"
    },
    {
      "title": "Fortress",
      "subtitle": "Apocrypha",
      "card_filename": "Heaven's Edge.png",
      "difficulty": "9-10",
      "modes": "All",
      "is_no_cmod": false,
      "banner_filename": "9-10.png"
    },
    {
      "title": "Holy Ground",
      "subtitle": "The Third Temple",
      "card_filename": "Third Temple.png",
      "difficulty": "10-1",
      "modes": "All",
      "is_no_cmod": true,
      "banner_filename": "10-1.png"
    },
    {
      "title": "The Third Temple",
      "subtitle": "The Third Temple",
      "card_filename": "Third Temple.png",
      "difficulty": "10-2",
      "modes": "All",
      "is_no_cmod": true,
      "banner_filename": "10-2.png"
    },
    {
      "title": "Spree",
      "subtitle": "Thousand Pound Butterfly",
      "card_filename": "butterfly.png",
      "difficulty": "11-1",
      "modes": "All",
      "is_no_cmod": false,
      "banner_filename": "11-1.png"
    },
    {
      "title": "Breakthrough",
      "subtitle": "Thousand Pound Butterfly",
      "card_filename": "butterfly.png",
      "difficulty": "11-2",
      "modes": "All",
      "is_no_cmod": false,
      "banner_filename": "11-2.png"
    },
    {
      "title": "Glide",
      "subtitle": "Thousand Pound Butterfly",
      "card_filename": "butterfly.png",
      "difficulty": "11-3",
      "modes": "All",
      "is_no_cmod": false,
      "banner_filename": "11-3.png"
    },
    {
      "title": "Closer",
      "subtitle": "Thousand Pound Butterfly",
      "card_filename": "butterfly.png",
      "difficulty": "11-4",
      "modes": "All",
      "is_no_cmod": false,
      "banner_filename": "11-4.png"
    },
    {
      "title": "Hike",
      "subtitle": "Thousand Pound Butterfly",
      "card_filename": "butterfly.png",
      "difficulty": "11-5",
      "modes": "All",
      "is_no_cmod": false,
      "banner_filename": "11-5.png"
    },
    {
      "title": "Switch",
      "subtitle": "Thousand Pound Butterfly",
      "card_filename": "butterfly.png",
      "difficulty": "11-6",
      "modes": "All",
      "is_no_cmod": false,
      "banner_filename": "11-6.png"
    },
    {
      "title": "Access",
      "subtitle": "Thousand Pound Butterfly",
      "card_filename": "butterfly.png",
      "difficulty": "11-7",
      "modes": "All",
      "is_no_cmod": false,
      "banner_filename": "11-7.png"
    },
    {
      "title": "Congregation",
      "subtitle": "Thousand Pound Butterfly",
      "card_filename": "butterfly.png",
      "difficulty": "11-8",
      "modes": "All",
      "is_no_cmod": false,
      "banner_filename": "11-8.png"
    },
    {
      "title": "Sequence",
      "subtitle": "Thousand Pound Butterfly",
      "card_filename": "butterfly.png",
      "difficulty": "11-9",
      "modes": "All",
      "is_no_cmod": false,
      "banner_filename": "11-9.png"
    },
    {
      "title": "Marathon",
      "subtitle": "Thousand Pound Butterfly",
      "card_filename": "butterfly.png",
      "difficulty": "11-10",
      "modes": "All",
      "is_no_cmod": false,
      "banner_filename": "11-10.png"
    },
    {
      "title": "Sacrifice",
      "subtitle": "Hand of God",
      "card_filename": "absolution.png",
      "difficulty": "12-1",
      "modes": "All",
      "is_no_cmod": true,
      "banner_filename": "12-1.png"
    },
    {
      "title": "Absolution",
      "subtitle": "Hand of God",
      "card_filename": "absolution.png",
      "difficulty": "12-2",
      "modes": "All",
      "is_no_cmod": true,
      "banner_filename": "12-2.png"
    },
    {
      "title": "Elevate Traversal I",
      "subtitle": "Red Sidequest",
      "card_filename": "Sheol.png",
      "difficulty": "R-1",
      "modes": "All",
      "is_no_cmod": false,
      "banner_filename": "R-1.png"
    },
    {
      "title": "Elevate Traversal II",
      "subtitle": "Red Sidequest",
      "card_filename": "Sheol.png",
      "difficulty": "R-2",
      "modes": "All",
      "is_no_cmod": false,
      "banner_filename": "R-2.png"
    },
    {
      "title": "Purify Traversal",
      "subtitle": "Red Sidequest",
      "card_filename": "Sheol.png",
      "difficulty": "R-3",
      "modes": "All",
      "is_no_cmod": false,
      "banner_filename": "R-3.png"
    },
    {
      "title": "Godspeed Traversal",
      "subtitle": "Red Sidequest",
      "card_filename": "Sheol.png",
      "difficulty": "R-4",
      "modes": "All",
      "is_no_cmod": false,
      "banner_filename": "R-4.png"
    },
    {
      "title": "Stomp Traversal",
      "subtitle": "Red Sidequest",
      "card_filename": "Sheol.png",
      "difficulty": "R-5",
      "modes": "All",
      "is_no_cmod": true,
      "banner_filename": "R-5.png"
    },
    {
      "title": "Fireball Traversal",
      "subtitle": "Red Sidequest",
      "card_filename": "Sheol.png",
      "difficulty": "R-6",
      "modes": "All",
      "is_no_cmod": true,
      "banner_filename": "R-6.png"
    },
    {
      "title": "Dominion Traversal",
      "subtitle": "Red Sidequest",
      "card_filename": "Sheol.png",
      "difficulty": "R-7",
      "modes": "All",
      "is_no_cmod": true,
      "banner_filename": "R-7.png"
    },
    {
      "title": "Book of Life Traversal",
      "subtitle": "Red Sidequest",
      "card_filename": "Sheol.png",
      "difficulty": "R-8",
      "modes": "All",
      "is_no_cmod": false,
      "banner_filename": "R-8.png"
    },
    {
      "title": "Doghouse",
      "subtitle": "Violet Sidequest",
      "card_filename": "Sheol.png",
      "difficulty": "V-1",
      "modes": "All",
      "is_no_cmod": false,
      "banner_filename": "V-1.png"
    },
    {
      "title": "Choker",
      "subtitle": "Violet Sidequest",
      "card_filename": "Sheol.png",
      "difficulty": "V-2",
      "modes": "All",
      "is_no_cmod": false,
      "banner_filename": "V-2.png"
    },
    {
      "title": "Chain",
      "subtitle": "Violet Sidequest",
      "card_filename": "Sheol.png",
      "difficulty": "V-3",
      "modes": "All",
      "is_no_cmod": false,
      "banner_filename": "V-3.png"
    },
    {
      "title": "Hellevator",
      "subtitle": "Violet Sidequest",
      "card_filename": "Sheol.png",
      "difficulty": "V-4",
      "modes": "All",
      "is_no_cmod": false,
      "banner_filename": "V-4.png"
    },
    {
      "title": "Razor",
      "subtitle": "Violet Sidequest",
      "card_filename": "Sheol.png",
      "difficulty": "V-5",
      "modes": "All",
      "is_no_cmod": false,
      "banner_filename": "V-5.png"
    },
    {
      "title": "All Seeing Eye",
      "subtitle": "Violet Sidequest",
      "card_filename": "Sheol.png",
      "difficulty": "V-6",
      "modes": "All",
      "is_no_cmod": false,
      "banner_filename": "V-6.png"
    },
    {
      "title": "Resident Saw I",
      "subtitle": "Violet Sidequest",
      "card_filename": "Sheol.png",
      "difficulty": "V-7",
      "modes": "All",
      "is_no_cmod": false,
      "banner_filename": "V-7.png"
    },
    {
      "title": "Resident Saw II",
      "subtitle": "Violet Sidequest",
      "card_filename": "Sheol.png",
      "difficulty": "V-8",
      "modes": "All",
      "is_no_cmod": false,
      "banner_filename": "V-8.png"
    },
    {
      "title": "Sunset Flip Powerbomb",
      "subtitle": "Yellow Sidequest",
      "card_filename": "Sheol.png",
      "difficulty": "Y-1",
      "modes": "All",
      "is_no_cmod": true,
      "banner_filename": "Y-1.png"
    },
    {
      "title": "Balloon Mountain",
      "subtitle": "Yellow Sidequest",
      "card_filename": "Sheol.png",
      "difficulty": "Y-2",
      "modes": "All",
      "is_no_cmod": false,
      "banner_filename": "Y-2.png"
    },
    {
      "title": "Climbing Gym",
      "subtitle": "Yellow Sidequest",
      "card_filename": "Sheol.png",
      "difficulty": "Y-3",
      "modes": "All",
      "is_no_cmod": true,
      "banner_filename": "Y-3.png"
    },
    {
      "title": "Fisherman Suplex",
      "subtitle": "Yellow Sidequest",
      "card_filename": "Sheol.png",
      "difficulty": "Y-4",
      "modes": "All",
      "is_no_cmod": true,
      "banner_filename": "Y-4.png"
    },
    {
      "title": "STF",
      "subtitle": "Yellow Sidequest",
      "card_filename": "Sheol.png",
      "difficulty": "Y-5",
      "modes": "All",
      "is_no_cmod": false,
      "banner_filename": "Y-5.png"
    },
    {
      "title": "Arena",
      "subtitle": "Yellow Sidequest",
      "card_filename": "Sheol.png",
      "difficulty": "Y-6",
      "modes": "All",
      "is_no_cmod": false,
      "banner_filename": "Y-6.png"
    },
    {
      "title": "Attitude Adjustment",
      "subtitle": "Yellow Sidequest",
      "card_filename": "Sheol.png",
      "difficulty": "Y-7",
      "modes": "All",
      "is_no_cmod": true,
      "banner_filename": "Y-7.png"
    },
    {
      "title": "Rocket",
      "subtitle": "Yellow Sidequest",
      "card_filename": "Sheol.png",
      "difficulty": "Y-8",
      "modes": "All",
      "is_no_cmod": false,
      "banner_filename": "Y-8.png"
    }
]